setup.py
db/__init__.py
db/deesupport.py
db.egg-info/PKG-INFO
db.egg-info/SOURCES.txt
db.egg-info/dependency_links.txt
db.egg-info/requires.txt
db.egg-info/top_level.txt
db/drivers/__init__.py
db/drivers/antipoolx.py
db/drivers/missing.py
db/drivers/psycopg2x.py
db/drivers/sqlite3x.py