Metadata-Version: 1.1
Name: db
Version: 0.0.4
Summary: Databases for Humans
Home-page: UNKNOWN
Author: John Evans
Author-email: lgastako@gmail.com
License: UNKNOWN
Platform: UNKNOWN
Provides: db
